zimasabus_sdk/__init__.py
zimasabus_sdk/examples/followup_example.py
zimasabus_sdk/examples/README.md
zimasabus_sdk/tests/__init__.py
zimasabus_sdk/tests/README.md
zimasabus_sdk/tests/test_followups.py
zimasabus_sdk/zimasa/__init__.py
zimasabus_sdk/zimasa/appointments.py
zimasabus_sdk/zimasa/followups.py
zimasabus_sdk/zmsystem.py
zmbus_sdk-0.1.8.dist-info/LICENSE
zmbus_sdk-0.1.8.dist-info/METADATA
zmbus_sdk-0.1.8.dist-info/WHEEL
zmbus_sdk-0.1.8.dist-info/RECORD
