Metadata-Version: 2.1
Name: zmbus-sdk
Version: 0.1.8
Summary: SDK for interacting with Zimasa medical systems
Home-page: https://github.com/dejinskunkworks/zimabus-sdk
License: MIT
Keywords: zimasa,zmbus,sdk
Author: Shikoli
Author-email: shikoli@turnkeyafrica.com
Requires-Python: >=3.8,<4.0
Classifier: Development Status :: 3 - Alpha
Classifier: Intended Audience :: Developers
Classifier: License :: OSI Approved :: MIT License
Classifier: Programming Language :: Python :: 3
Classifier: Programming Language :: Python :: 3.8
Classifier: Programming Language :: Python :: 3.9
Classifier: Programming Language :: Python :: 3.10
Classifier: Programming Language :: Python :: 3.11
Classifier: Programming Language :: Python :: 3.12
Classifier: Programming Language :: Python :: 3.13
Requires-Dist: exrex
Requires-Dist: pydantic (==2.*)
Requires-Dist: requests
Project-URL: Repository, https://github.com/dejinskunkworks/zimabus-sdk
